CHANGELOG.txt
MANIFEST.in
README.md
example2.py
example3.py
example5.py
example6.py
example_draw.py
requirements.txt
setup.py
bin/ctm
bin/samplegen
bin/smc
examples/__init__.py
examples/estimation_by_pruning.py
examples/estimation_using_bic.py
examples/estimation_using_smc.py
examples/linguistic_case_study.py
examples/run_ml.sh
examples/run_ml_fast_1.sh
examples/run_ml_fast_2.sh
examples/sim_model1_matlab_compat_off6
examples/sim_model1_perl_compat_off0
examples/sim_model2_csizar_and_talata_off0
examples/sim_model2_csizar_and_talata_off6
examples/sim_model2_perl_compat_off0
examples/simulation_study.py
examples/linguistic_case_study/__init__.py
examples/linguistic_case_study/folha.txt
examples/linguistic_case_study/folha.txt.bkp
examples/linguistic_case_study/publico.txt
examples/linguistic_case_study/publico.txt.bkp
examples/notebooks/1. Context trees and BIC.ipynb
examples/notebooks/2. Smallest Maximizer Criterion.ipynb
examples/notebooks/4. Linguistic case study.ipynb
examples/notebooks/7. Visualization.ipynb
examples/notebooks/.ipynb_checkpoints/1. Context trees and BIC-checkpoint.ipynb
examples/notebooks/.ipynb_checkpoints/2. Smallest Maximizer Criterion-checkpoint.ipynb
examples/notebooks/.ipynb_checkpoints/4. Linguistic case study-checkpoint.ipynb
examples/notebooks/.ipynb_checkpoints/7. Visualization-checkpoint.ipynb
examples/notebooks/.ipynb_checkpoints/tf-idf investigation-checkpoint.ipynb
examples/notebooks/resources/samples/model1_5000_s001.txt
examples/notebooks/simulations/Results.ipynb
examples/notebooks/simulations/.ipynb_checkpoints/Results-checkpoint.ipynb
examples/notebooks/simulations/data/model1_10000.csv
examples/notebooks/simulations/data/model1_20000.csv
examples/notebooks/simulations/data/model1_5000.csv
examples/notebooks/simulations/data/model2_10000.csv
examples/notebooks/simulations/data/model2_20000.csv
examples/notebooks/simulations/data/model2_5000.csv
examples/simulation_study/__init__.py
examples/simulation_study/models.py
g4l_smc.egg-info/PKG-INFO
g4l_smc.egg-info/SOURCES.txt
g4l_smc.egg-info/dependency_links.txt
g4l_smc.egg-info/requires.txt
g4l_smc.egg-info/top_level.txt
