Metadata-Version: 2.1
Name: g4l-smc
Version: 0.0.2
Summary: Context tree estimation using the Smallest Maximizer Criterion (SMC)
Home-page: https://github.com/arthurtofani/smallest_maximizer_criterion
Author: Arthur Tofani
Author-email: arthur.tofani@usp.br
License: UNKNOWN
Platform: UNKNOWN
Requires-Python: >=3.7
